Workbook

Sheet Replacement Costs
A1: Photo | B1: Floor | C1: Room | D1: Item (as photographed) | E1: Qty | F1: Replacement Equivalent (New) | G1: Retailer | H1: Link | I1: Unit Price New | J1: Extended New | K1: Duplicate? | L1: Pricing Basis / Notes | M1: Pack-out Est Lo (used) | N1: Pack-out Est Hi (used)
A2: IMG_2478 | B2: 1st | C2: Office | D2: Box of film/slide accessories | E2: 1 | F2: Film reel/slide storage accessory set (new) | G2: Amazon | H2: view | I2: 25 | J2: =E2*I2 | L2: estimated typical new retail | M2: 5 | N2: 15
A3: IMG_2478 | B3: 1st | C3: Office | D3: Lava lamp, brass/gold base, clear fluid | E3: 1 | F3: Lava the Original 14.5-in Gold Metallic Base Lamp | G3: Walmart | H3: view | I3: 19.99 | J3: =E3*I3 | L3: Walmart snippet $15.29 (OOS); typical in-stock new ~$20 | M3: 15 | N3: 40
A4: IMG_2478 | B4: 1st | C4: Office | D4: Vintage 8mm/16mm film projector (brand plate illegible) | E4: 1 | F4: KODAK REELZ 8mm/Super 8 film digitizer (new functional equivalent of vintage projector) | G4: Amazon | H4: view | I4: 299.99 | J4: =E4*I4 | L4: search snippets showed $320-$400 range for new film digitizers | working condition unknown | M4: 40 | N4: 120
A5: IMG_2479 | B5: 1st | C5: Office | D5: Lot of assorted books/box sets on shelf | E5: 1 | F5: Assorted new books/box sets (~12 volumes at ~$10 each) | G5: Amazon | H5: view | I5: 120 | J5: =E5*I5 | L5: estimated typical new retail for equivalent quantity | M5: 30 | N5: 80
A6: IMG_2479 | B6: 1st | C6: Office | D6: Oak captain's chair (barrel back) | E6: 1 | F6: New solid oak barrel-back captain's dining chair | G6: Wayfair | H6: view | I6: 180 | J6: =E6*I6 | L6: typical new retail for this category | M6: 60 | N6: 150
A7: IMG_2479 | B7: 1st | C7: Office | D7: Tall dark-red wood bookshelf | E7: 1 | F7: Sauder Select 5-shelf wood bookcase, cherry finish, 72 in | G7: Walmart | H7: view | I7: 119 | J7: =E7*I7 | L7: typical new retail; comparable 72-in cherry bookcases $119-$255 in search results | partially visible at left | M7: 40 | N7: 100
A8: IMG_2480 | B8: 1st | C8: Office | D8: QFX J-220BT retro Bluetooth cassette boombox | E8: 1 | F8: QFX J-220BT retro Bluetooth cassette boombox (same model, new) | G8: Walmart | H8: view | I8: 44.99 | J8: =E8*I8 | L8: price from search result snippet | M8: 30 | N8: 60
A9: IMG_2481 | B9: 1st | C9: Office | D9: Blister-pack kit (small tools/brush/pins) | E9: 1 | F9: Small tool/brush/pin accessory kit (new) | G9: Amazon | H9: view | I9: 12 | J9: =E9*I9 | L9: estimated typical new retail | M9: 5 | N9: 15
A10: IMG_2481 | B10: 1st | C10: Office | D10: Cardboard cat scratcher lounge | E10: 1 | F10: ScratchMe 2-in-1 cardboard cat scratcher lounge bed | G10: Walmart | H10: view | I10: 18.95 | J10: =E10*I10 | L10: price from search result snippet | M10: 10 | N10: 25
A11: IMG_2481 | B11: 1st | C11: Office | D11: NOCO GCP1 AC port plug (in box) | E11: 1 | F11: NOCO GCP1 15A AC Port Plug (same model, new) | G11: Amazon | H11: view | I11: 22.95 | J11: =E11*I11 | L11: price from search result snippet | M11: 15 | N11: 30
A12: IMG_2481 | B12: 1st | C12: Office | D12: Rolled yoga mats | E12: 2 | F12: BalanceFrom 1/4-in high density non-slip yoga mat with strap | G12: Walmart | H12: view | I12: 21.99 | J12: =E12*I12 | L12: price from search result snippet (per mat) | M12: 10 | N12: 30
A13: IMG_2481 | B13: 1st | C13: Office | D13: Wicker basket with misc contents (cat toy, cords, sundries) | E13: 1 | F13: Wicker storage basket plus misc sundries (new) | G13: Walmart | H13: view | I13: 25 | J13: =E13*I13 | L13: estimated typical new retail | M13: 10 | N13: 25
... A72: IMG_2494 | B72: 1st | C72: Dining Room | D72: Wrought iron two-bottle caddy/stand | E72: 1 | F72: Handcrafted iron 2-bottle wine caddy (Van's Gifts) | G72: Amazon | H72: view | I72: 35 | J72: =E72*I72 | L72: estimated typical new retail; product found via search | M72: 10 | N72: 30
A73: IMG_2495 | B73: 1st | C73: Dining Room | D73: Absinthe bottle lot in wood crate (same as IMG_2494) | E73: 1 | F73: Grande Absente 750ml + minis + crate (new lot; duplicate of IMG_2494 item) | G73: Total Wine | H73: view | I73: 150 | J73: =E73*I73 | K73: Dup | L73: Grande Absente $79.99 from search snippet + minis/second bottle/crate estimated | M73: 30 | N73: 80
A74: IMG_2495 | B74: 1st | C74: Dining Room | D74: Glass/crystal candlesticks (same pair) | E74: 2 | F74: Crystal glass candlestick holder (unit; duplicate pair from IMG_2494) | G74: Amazon | H74: view | I74: 15 | J74: =E74*I74 | K74: Dup | L74: price from search results (sets of 2 in $25-35 tier) | M74: 10 | N74: 30
A75: IMG_2495 | B75: 1st | C75: Dining Room | D75: Misc bar-top lot (same) | E75: 1 | F75: Assorted new bar accessories/novelty decor lot (duplicate of IMG_2494 item) | G75: Amazon | H75: view | I75: 25 | J75: =E75*I75 | K75: Dup | L75: estimated typical new retail for equivalent lot | M75: 10 | N75: 25
A76: IMG_2495 | B76: 1st | C76: Dining Room | D76: Red star-shaped side table (same as IMG_2492) | E76: 1 | F76: Solid wood novelty/accent end table on metal base (duplicate of IMG_2492 item) | G76: Wayfair | H76: view | I76: 70 | J76: =E76*I76 | K76: Dup | L76: typical new retail for handcrafted wood accent table | M76: 20 | N76: 60
A77: IMG_2495 | B77: 1st | C77: Dining Room | D77: Silver-plated round tray (same) | E77: 1 | F77: Silver-plated round serving tray (duplicate of IMG_2494 item) | G77: Amazon | H77: view | I77: 35 | J77: =E77*I77 | K77: Dup | L77: search snippet: silver plated trays from ~$39.95 | M77: 10 | N77: 30
A78: IMG_2495 | B78: 1st | C78: Dining Room | D78: Stainless cocktail shaker tin (same) | E78: 1 | F78: Thyme & Table 18oz stainless cocktail shaker (duplicate of IMG_2494 item) | G78: Walmart | H78: view | I78: 13 | J78: =E78*I78 | K78: Dup | L78: price from search result snippet ($12.99-$16.99) | M78: 5 | N78: 15
A79: IMG_2495 | B79: 1st | C79: Dining Room | D79: Textured glass hurricane/vase (same) | E79: 1 | F79: Textured glass hurricane candle holder/vase (duplicate of IMG_2494 item) | G79: Target | H79: view | I79: 25 | J79: =E79*I79 | K79: Dup | L79: search snippets: Target budget to Crate&Barrel $69.95; mid-low estimate | M79: 5 | N79: 15
A80: IMG_2495 | B80: 1st | C80: Dining Room | D80: Vintage carved/ebonized black table lamp (same as IMG_2494) | E80: 1 | F80: Black traditional carved-style table lamp (new; duplicate of IMG_2494 item) | G80: Wayfair | H80: view | I80: 70 | J80: =E80*I80 | K80: Dup | L80: typical new retail for this category | M80: 25 | N80: 75
A81: IMG_2495 | B81: 1st | C81: Dining Room | D81: Wooden home bar cabinet with drop-leaf counter (same as IMG_2494) | E81: 1 | F81: Farmhouse bar cabinet with folding/drop-leaf top (new; duplicate of IMG_2494 item) | G81: Wayfair | H81: view | I81: 350 | J81: =E81*I81 | K81: Dup | L81: typical new retail for this category | M81: 150 | N81: 400
A82: IMG_2495 | B82: 1st | C82: Dining Room | D82: Wrought iron two-bottle caddy/stand (same) | E82: 1 | F82: Handcrafted iron 2-bottle wine caddy (duplicate of IMG_2494 item) | G82: Amazon | H82: view | I82: 35 | J82: =E82*I82 | K82: Dup | L82: estimated typical new retail; product found via search | M82: 10 | N82: 30
A83: IMG_2496 | B83: 1st | C83: Dining Room | D83: Vintage Last Supper print in ornate gilt gesso frame (~40x24 in) | E83: 1 | F83: Leonardo da Vinci The Last Supper 40x24 gold ornate framed canvas print | G83: Amazon | H83: view | I83: 140 | J83: =E83*I83 | L83: estimated typical new retail; exact product found via search, no snippet price | M83: 75 | N83: 250
A84: IMG_2497 | B84: 1st | C84: Dining Room | D84: Gilt-framed pin-up mixed-media print (~14x14 in) | E84: 1 | F84: Gilt-framed art print ~14x14 (new) | G84: Amazon | H84: view | I84: 35 | J84: =E84*I84 | L84: estimated typical new retail | M84: 20 | N84: 60
A85: IMG_2497 | B85: 1st | C85: Dining Room | D85: Retro red-face wall clock, cream case | E85: 1 | F85: Westclox Retro 1950s 9.5-in red kitchen wall clock | G85: Amazon | H85: view | I85: 25 | J85: =E85*I85 | L85: product from search results; typical new retail | M85: 10 | N85: 25
A86: IMG_2498 | B86: 1st | C86: Dining Room | D86: Antique industrial swivel stool (metal base, wood top) | E86: 1 | F86: Best Choice Products vintage industrial adjustable swivel stool, wood top/metal base (new) | G86: Amazon | H86: view | I86: 70 | J86: =E86*I86 | L86: typical new retail for this category (sets of 2 run $120-150) | M86: 40 | N86: 120
A87: IMG_2498 | B87: 1st | C87: Dining Room | D87: Plastic organizer bins with markers, pens and vape cartridges (lot) | E87: 1 | F87: Plastic desktop organizer bins plus marker/pen assortment (new) | G87: Walmart | H87: view | I87: 20 | J87: =E87*I87 | L87: estimated typical new retail for equivalent lot | M87: 5 | N87: 15
A88: IMG_2498 | B88: 1st | C88: Dining Room | D88: Vintage electrical switch box / bell-ringer device with lever | E88: 1 | F88: New industrial-style knife-switch / doorbell transformer box (functional equivalent of vintage device) | G88: Amazon | H88: view | I88: 35 | J88: =E88*I88 | L88: estimated typical new retail | M88: 20 | N88: 60
A89: IMG_2498 | B89: 1st | C89: Dining Room | D89: Vintage wooden ballot/collection box with coin slot | E89: 1 | F89: Displays2go locking wood suggestion/ballot box with slot (new equivalent of vintage box) | G89: Amazon | H89: view | I89: 45 | J89: =E89*I89 | L89: typical new retail for this category | M89: 30 | N89: 80
A90: IMG_2499 | B90: 1st | C90: Dining Room | D90: E-cigarette/vape kit in zip case | E90: 1 | F90: E-cigarette starter kit with zip carrying case (new) | G90: Element Vape (online) | H90: view | I90: 35 | J90: =E90*I90 | L90: estimated typical new retail | M90: 10 | N90: 30
A91: IMG_2499 | B91: 1st | C91: Dining Room | D91: Estate tobacco pipes and smoking accessories (lot) | E91: 1 | F91: New briar/corn-cob tobacco pipe plus accessories kit (equivalent of estate pipe lot) | G91: Amazon | H91: view | I91: 40 | J91: =E91*I91 | L91: estimated typical new retail | M91: 10 | N91: 40
A92: IMG_2499 | B92: 1st | C92: Dining Room | D92: Grande Absente absinthe bottle (opened, partial) | E92: 1 | F92: Grande Absente Absinthe Originale 750ml (new bottle) | G92: Total Wine | H92: view | I92: 82 | J92: =E92*I92 | L92: price from search result snippet ($81.99 Total Wine) | M92: 15 | N92: 40
A93: IMG_2499 | B93: 1st | C93: Dining Room | D93: Large spirits bottle with fruit label (opened) | E93: 1 | F93: Fruit liqueur/brandy 750ml (new bottle) | G93: Total Wine | H93: view | I93: 25 | J93: =E93*I93 | L93: estimated typical new retail | M93: 5 | N93: 20
A94: IMG_2499 | B94: 1st | C94: Dining Room | D94: Leather bifold wallet | E94: 1 | F94: Amazon Essentials men's leather bifold wallet (new) | G94: Amazon | H94: view | I94: 18 | J94: =E94*I94 | L94: price from search result snippet ($18.10) | M94: 5 | N94: 20
... A416: IMG_2578 | B416: 3rd | C416: Bathroom | D416: PetSafe ScoopFree automatic self-cleaning litter box with purple hood | E416: 1 | F416: PetSafe ScoopFree Crystal self-cleaning litter box with privacy hood (new) | G416: Amazon | H416: view | I416: 239.99 | J416: =E416*I416 | L416: price from search result snippet (hooded model $239.99) | Powered on; includes disposable litter tray | M416: 50 | N416: 110
D417: TOTAL (all rows) | J417: =SUM(J2:J416)
D418: TOTAL excluding duplicate-angle rows | J418: =SUMIF(K2:K416,"",J2:J416)

Sheet Summary
A1: 899 Virginia Park St — Contents Replacement Cost (Buy New)
A2: Claim 061004792 · Liberty Mutual · prepared 07/24/2026 from the 100 pack-out photos (415 line items)
A4: Line items priced | C4: =COUNTA('Replacement Costs'!A2:A416)
A5: Total replacement cost, new (all rows) | C5: ='Replacement Costs'!J417
A6: Total excluding duplicate camera-angle rows | C6: ='Replacement Costs'!J418
A7: Pack-out used-value estimate range (lo–hi) | C7: =SUM('Replacement Costs'!M2:M416) | D7: =SUM('Replacement Costs'!N2:N416)
A9: By floor (excluding duplicate rows)
A10: 1st | C10: =SUMIFS('Replacement Costs'!J2:J416,'Replacement Costs'!B2:B416,A10,'Replacement Costs'!K2:K416,"")
A11: 2nd | C11: =SUMIFS('Replacement Costs'!J2:J416,'Replacement Costs'!B2:B416,A11,'Replacement Costs'!K2:K416,"")
A12: 3rd | C12: =SUMIFS('Replacement Costs'!J2:J416,'Replacement Costs'!B2:B416,A12,'Replacement Costs'!K2:K416,"")
A13: Basement | C13: =SUMIFS('Replacement Costs'!J2:J416,'Replacement Costs'!B2:B416,A13,'Replacement Costs'!K2:K416,"")
A15: How to read this workbook
A16: • Each row = one item identified in a pack-out photo (AI-assisted inventory from the photo map portal).
A17: • Unit Price New = current price to buy an equivalent item NEW at the linked US retailer (searched 07/24/2026).
A18: • Link column: direct product page where one was found, otherwise a retailer search pre-filled with the item description.
A19: • Vintage/antique pieces are priced as the closest NEW functional equivalent (noted in the Replacement column).
A20: • Rows marked "Dup" show the same items from a second camera angle and are excluded from the second total.
A21: • Pricing Basis column says whether the price came from a live search result or is a typical-new-retail estimate.
A22: • Pack-out Est columns carry the portal's original used-value (ACV-style) range for comparison.
